{"19-4b3r4":{"index":1,"id":"19-4b3r4","text":"dasd","date_added":1507857035961,"done":true,"rating":0,"time_done":1507857040841},"18-l4s7c":{"index":2,"id":"18-l4s7c","text":"adsa","date_added":1507857033488,"done":true,"rating":0,"time_done":1507857041849},"17-epglo":{"index":3,"id":"17-epglo","text":"asda","date_added":1507857032541,"done":true,"rating":0,"time_done":1507857042760},"16-da7o7":{"index":4,"id":"16-da7o7","text":"waaa","date_added":1507857031498,"done":true,"rating":0,"time_done":1507857043668},"15-c7mag":{"index":5,"id":"15-c7mag","text":"s","date_added":1507857022825,"done":true,"rating":0,"time_done":1507857044840},"14-g5iab":{"index":6,"id":"14-g5iab","text":"test","date_added":1507857018438,"done":false,"rating":0},"13-r5b98":{"index":7,"id":"13-r5b98","text":"test","date_added":1507845847975,"done":false,"rating":"0","time_done":1507856697542},"12-ph37p":{"index":8,"id":"12-ph37p","text":"Test","date_added":1507845815773,"done":false,"rating":0},"11-r3d8f":{"index":9,"id":"11-r3d8f","text":"test2","date_added":1507845759187,"done":false,"rating":0,"deleted":"2017-10-12T22:02:44.347Z"},"10-l79cm":{"index":10,"id":"10-l79cm","text":"test","date_added":1507845756909,"done":false,"rating":0,"deleted":"2017-10-12T22:02:46.496Z"},"9-a8fp0":{"index":11,"id":"9-a8fp0","text":"r213","date_added":1506563139357,"done":false,"rating":"2"},"8-7r8am":{"index":12,"id":"8-7r8am","text":"test23","date_added":1506563060964,"done":false,"rating":0,"deleted":"2017-10-12T22:02:48.518Z"},"7-e4gig":{"index":13,"id":"7-e4gig","text":"test22123","date_added":1506562893288,"done":false,"rating":"0","deleted":"2017-10-12T22:02:50.388Z"},"6-h48p4":{"index":14,"id":"6-h48p4","text":"test","date_added":1506562617977,"done":false,"rating":"0","deleted":"2017-10-12T22:02:52.558Z"},"5-74dj2":{"index":15,"id":"5-74dj2","text":"test\t\t\t","date_added":1506562508004,"done":false,"rating":0,"deleted":"2017-09-28T01:35:13.577Z"},"4-cb62k":{"index":16,"id":"4-cb62k","text":"test\t\t\t\t","date_added":1506562498553,"done":false,"rating":"0","deleted":"2017-10-12T22:02:54.660Z"},"3-47ks1":{"id":"3-47ks1","date_added":1506560986445,"done":false,"rating":"4","index":17,"deleted":"2017-09-28T01:35:02.059Z"},"2-7jpkf":{"id":"2-7jpkf","date_added":1506560793603,"done":false,"index":18,"deleted":"2017-09-28T01:35:11.258Z"},"1-a5r6e":{"index":19,"id":"1-a5r6e","text":"test","date_added":1506560790346,"done":false,"rating":"0"},"0-3i85b":{"index":20,"id":"0-3i85b","text":"test2222","date_added":1506560751154,"done":true,"rating":"0"}}